[
  {
    "fitness": -0.9192,
    "avg_sim": 0.35899999737739563,
    "avg_cc": 0.1306,
    "avg_kl": 1.4088000059127808,
    "base_weights": {
      "contrast_edge_luminance_laplacian": 0.4413,
      "contrast_edge_luminance_sobel": 0.6057,
      "contrast_edge_color_sobel": 0.3743,
      "contrast_edge_color_gradient": 0.4037,
      "contrast_region_color_slic": 0.1357,
      "contrast_texture_gabor": 0.0214,
      "contrast_texture_lbp": 0.0473,
      "contrast_texture_entropy": 0.6743,
      "symmetry_watershed": 0.0999,
      "symmetry_felzenszwalb": 0.128,
      "symmetry_seeded_region": 0.3054,
      "symmetry_superpixel_preproc": 0.2061,
      "symmetry_superpixel": 0.0856,
      "symmetry_watershed_h": 0.8898,
      "symmetry_felzenszwalb_h": 0.1504,
      "symmetry_seeded_region_h": 0.6272,
      "symmetry_superpixel_preproc_h": 0.1703,
      "symmetry_superpixel_h": 0.4706,
      "isolation_color_global_abs": 0.5151,
      "isolation_color_local_abs": 0.774,
      "isolation_color_local_multi": 0.3652,
      "isolation_intensity_global_abs": 0.0143,
      "isolation_intensity_local_abs": 0.9644,
      "isolation_intensity_local_multi": 0.4568,
      "isolation_tex_entropy_global_abs": 0.6578,
      "isolation_tex_entropy_local_abs": 0.2537,
      "isolation_tex_entropy_local_multi": 0.9442,
      "isolation_tex_lbp_global_abs": 0.3994,
      "isolation_tex_lbp_local_abs": 0.0572,
      "isolation_tex_lbp_local_multi": 0.362,
      "isolation_tex_gab_global_abs": 0.3542,
      "isolation_tex_gab_local_abs": 0.6361,
      "isolation_tex_gab_local_multi": 0.6698,
      "grouping_color_histogram_bins": 0.748,
      "grouping_line_hough": 0.9863
    },
    "modulation_weights": {
      "contrast": [
        0.6625,
        0.2803,
        0.0727
      ],
      "symmetry": [
        0.2362,
        0.1146,
        0.1205
      ],
      "isolation": [
        0.3836,
        0.2972,
        0.6026
      ],
      "grouping": [
        0.036,
        0.7703,
        0.0475
      ]
    }
  },
  {
    "fitness": -0.9192,
    "avg_sim": 0.35899999737739563,
    "avg_cc": 0.1306,
    "avg_kl": 1.4088000059127808,
    "base_weights": {
      "contrast_edge_luminance_laplacian": 0.4413,
      "contrast_edge_luminance_sobel": 0.6057,
      "contrast_edge_color_sobel": 0.3743,
      "contrast_edge_color_gradient": 0.4037,
      "contrast_region_color_slic": 0.1357,
      "contrast_texture_gabor": 0.0214,
      "contrast_texture_lbp": 0.0473,
      "contrast_texture_entropy": 0.6743,
      "symmetry_watershed": 0.0999,
      "symmetry_felzenszwalb": 0.128,
      "symmetry_seeded_region": 0.3054,
      "symmetry_superpixel_preproc": 0.2061,
      "symmetry_superpixel": 0.0856,
      "symmetry_watershed_h": 0.8898,
      "symmetry_felzenszwalb_h": 0.1504,
      "symmetry_seeded_region_h": 0.6272,
      "symmetry_superpixel_preproc_h": 0.1703,
      "symmetry_superpixel_h": 0.4706,
      "isolation_color_global_abs": 0.5151,
      "isolation_color_local_abs": 0.774,
      "isolation_color_local_multi": 0.3652,
      "isolation_intensity_global_abs": 0.0143,
      "isolation_intensity_local_abs": 0.9644,
      "isolation_intensity_local_multi": 0.4568,
      "isolation_tex_entropy_global_abs": 0.6578,
      "isolation_tex_entropy_local_abs": 0.2537,
      "isolation_tex_entropy_local_multi": 0.9442,
      "isolation_tex_lbp_global_abs": 0.3994,
      "isolation_tex_lbp_local_abs": 0.0572,
      "isolation_tex_lbp_local_multi": 0.362,
      "isolation_tex_gab_global_abs": 0.3542,
      "isolation_tex_gab_local_abs": 0.6361,
      "isolation_tex_gab_local_multi": 0.6698,
      "grouping_color_histogram_bins": 0.748,
      "grouping_line_hough": 0.9863
    },
    "modulation_weights": {
      "contrast": [
        0.6625,
        0.2803,
        0.0727
      ],
      "symmetry": [
        0.2362,
        0.1146,
        0.1205
      ],
      "isolation": [
        0.3836,
        0.2972,
        0.6026
      ],
      "grouping": [
        0.036,
        0.7703,
        0.0475
      ]
    }
  },
  {
    "fitness": -0.9284,
    "avg_sim": 0.35740000009536743,
    "avg_cc": 0.128,
    "avg_kl": 1.413699984550476,
    "base_weights": {
      "contrast_edge_luminance_laplacian": 0.8173,
      "contrast_edge_luminance_sobel": 0.6774,
      "contrast_edge_color_sobel": 0.6574,
      "contrast_edge_color_gradient": 0.7453,
      "contrast_region_color_slic": 0.9985,
      "contrast_texture_gabor": 0.1093,
      "contrast_texture_lbp": 0.0221,
      "contrast_texture_entropy": 0.9244,
      "symmetry_watershed": 0.2454,
      "symmetry_felzenszwalb": 0.7783,
      "symmetry_seeded_region": 0.2108,
      "symmetry_superpixel_preproc": 0.3593,
      "symmetry_superpixel": 0.623,
      "symmetry_watershed_h": 0.323,
      "symmetry_felzenszwalb_h": 0.3504,
      "symmetry_seeded_region_h": 0.9439,
      "symmetry_superpixel_preproc_h": 0.2223,
      "symmetry_superpixel_h": 0.8855,
      "isolation_color_global_abs": 0.1031,
      "isolation_color_local_abs": 0.4448,
      "isolation_color_local_multi": 0.2798,
      "isolation_intensity_global_abs": 0.0438,
      "isolation_intensity_local_abs": 0.9895,
      "isolation_intensity_local_multi": 0.5855,
      "isolation_tex_entropy_global_abs": 0.5946,
      "isolation_tex_entropy_local_abs": 0.0799,
      "isolation_tex_entropy_local_multi": 0.2817,
      "isolation_tex_lbp_global_abs": 0.4019,
      "isolation_tex_lbp_local_abs": 0.6926,
      "isolation_tex_lbp_local_multi": 0.7292,
      "isolation_tex_gab_global_abs": 0.511,
      "isolation_tex_gab_local_abs": 0.3453,
      "isolation_tex_gab_local_multi": 0.9571,
      "grouping_color_histogram_bins": 0.4054,
      "grouping_line_hough": 0.7002
    },
    "modulation_weights": {
      "contrast": [
        0.7787,
        0.704,
        0.1707
      ],
      "symmetry": [
        0.1318,
        0.449,
        0.3412
      ],
      "isolation": [
        0.9451,
        0.7261,
        0.5171
      ],
      "grouping": [
        0.2979,
        0.9355,
        0.7796
      ]
    }
  },
  {
    "fitness": -0.9284,
    "avg_sim": 0.35740000009536743,
    "avg_cc": 0.128,
    "avg_kl": 1.413699984550476,
    "base_weights": {
      "contrast_edge_luminance_laplacian": 0.8173,
      "contrast_edge_luminance_sobel": 0.6774,
      "contrast_edge_color_sobel": 0.6574,
      "contrast_edge_color_gradient": 0.7453,
      "contrast_region_color_slic": 0.9985,
      "contrast_texture_gabor": 0.1093,
      "contrast_texture_lbp": 0.0221,
      "contrast_texture_entropy": 0.9244,
      "symmetry_watershed": 0.2454,
      "symmetry_felzenszwalb": 0.7783,
      "symmetry_seeded_region": 0.2108,
      "symmetry_superpixel_preproc": 0.3593,
      "symmetry_superpixel": 0.623,
      "symmetry_watershed_h": 0.323,
      "symmetry_felzenszwalb_h": 0.3504,
      "symmetry_seeded_region_h": 0.9439,
      "symmetry_superpixel_preproc_h": 0.2223,
      "symmetry_superpixel_h": 0.8855,
      "isolation_color_global_abs": 0.1031,
      "isolation_color_local_abs": 0.4448,
      "isolation_color_local_multi": 0.2798,
      "isolation_intensity_global_abs": 0.0438,
      "isolation_intensity_local_abs": 0.9895,
      "isolation_intensity_local_multi": 0.5855,
      "isolation_tex_entropy_global_abs": 0.5946,
      "isolation_tex_entropy_local_abs": 0.0799,
      "isolation_tex_entropy_local_multi": 0.2817,
      "isolation_tex_lbp_global_abs": 0.4019,
      "isolation_tex_lbp_local_abs": 0.6926,
      "isolation_tex_lbp_local_multi": 0.7292,
      "isolation_tex_gab_global_abs": 0.511,
      "isolation_tex_gab_local_abs": 0.3453,
      "isolation_tex_gab_local_multi": 0.9571,
      "grouping_color_histogram_bins": 0.4054,
      "grouping_line_hough": 0.7002
    },
    "modulation_weights": {
      "contrast": [
        0.7787,
        0.704,
        0.1707
      ],
      "symmetry": [
        0.1318,
        0.449,
        0.3412
      ],
      "isolation": [
        0.9451,
        0.7261,
        0.5171
      ],
      "grouping": [
        0.2979,
        0.9355,
        0.7796
      ]
    }
  },
  {
    "fitness": -0.94,
    "avg_sim": 0.3569999933242798,
    "avg_cc": 0.1273,
    "avg_kl": 1.424299955368042,
    "base_weights": {
      "contrast_edge_luminance_laplacian": 0.9229,
      "contrast_edge_luminance_sobel": 0.2548,
      "contrast_edge_color_sobel": 0.9477,
      "contrast_edge_color_gradient": 0.8426,
      "contrast_region_color_slic": 0.1816,
      "contrast_texture_gabor": 0.6268,
      "contrast_texture_lbp": 0.6357,
      "contrast_texture_entropy": 0.6694,
      "symmetry_watershed": 0.6245,
      "symmetry_felzenszwalb": 0.5806,
      "symmetry_seeded_region": 0.8496,
      "symmetry_superpixel_preproc": 0.4915,
      "symmetry_superpixel": 0.6637,
      "symmetry_watershed_h": 0.0358,
      "symmetry_felzenszwalb_h": 0.4434,
      "symmetry_seeded_region_h": 0.4668,
      "symmetry_superpixel_preproc_h": 0.7468,
      "symmetry_superpixel_h": 0.0752,
      "isolation_color_global_abs": 0.6496,
      "isolation_color_local_abs": 0.6421,
      "isolation_color_local_multi": 0.3412,
      "isolation_intensity_global_abs": 0.8152,
      "isolation_intensity_local_abs": 0.4779,
      "isolation_intensity_local_multi": 0.3092,
      "isolation_tex_entropy_global_abs": 0.8973,
      "isolation_tex_entropy_local_abs": 0.0546,
      "isolation_tex_entropy_local_multi": 0.4698,
      "isolation_tex_lbp_global_abs": 0.6251,
      "isolation_tex_lbp_local_abs": 0.8851,
      "isolation_tex_lbp_local_multi": 0.6151,
      "isolation_tex_gab_global_abs": 0.045,
      "isolation_tex_gab_local_abs": 0.9959,
      "isolation_tex_gab_local_multi": 0.9667,
      "grouping_color_histogram_bins": 0.6577,
      "grouping_line_hough": 0.3787
    },
    "modulation_weights": {
      "contrast": [
        0.7858,
        0.9993,
        0.6977
      ],
      "symmetry": [
        0.0282,
        0.2477,
        0.588
      ],
      "isolation": [
        0.1455,
        0.4244,
        0.6713
      ],
      "grouping": [
        0.6256,
        0.4731,
        0.4453
      ]
    }
  },
  {
    "fitness": -0.94,
    "avg_sim": 0.3569999933242798,
    "avg_cc": 0.1273,
    "avg_kl": 1.424299955368042,
    "base_weights": {
      "contrast_edge_luminance_laplacian": 0.9229,
      "contrast_edge_luminance_sobel": 0.2548,
      "contrast_edge_color_sobel": 0.9477,
      "contrast_edge_color_gradient": 0.8426,
      "contrast_region_color_slic": 0.1816,
      "contrast_texture_gabor": 0.6268,
      "contrast_texture_lbp": 0.6357,
      "contrast_texture_entropy": 0.6694,
      "symmetry_watershed": 0.6245,
      "symmetry_felzenszwalb": 0.5806,
      "symmetry_seeded_region": 0.8496,
      "symmetry_superpixel_preproc": 0.4915,
      "symmetry_superpixel": 0.6637,
      "symmetry_watershed_h": 0.0358,
      "symmetry_felzenszwalb_h": 0.4434,
      "symmetry_seeded_region_h": 0.4668,
      "symmetry_superpixel_preproc_h": 0.7468,
      "symmetry_superpixel_h": 0.0752,
      "isolation_color_global_abs": 0.6496,
      "isolation_color_local_abs": 0.6421,
      "isolation_color_local_multi": 0.3412,
      "isolation_intensity_global_abs": 0.8152,
      "isolation_intensity_local_abs": 0.4779,
      "isolation_intensity_local_multi": 0.3092,
      "isolation_tex_entropy_global_abs": 0.8973,
      "isolation_tex_entropy_local_abs": 0.0546,
      "isolation_tex_entropy_local_multi": 0.4698,
      "isolation_tex_lbp_global_abs": 0.6251,
      "isolation_tex_lbp_local_abs": 0.8851,
      "isolation_tex_lbp_local_multi": 0.6151,
      "isolation_tex_gab_global_abs": 0.045,
      "isolation_tex_gab_local_abs": 0.9959,
      "isolation_tex_gab_local_multi": 0.9667,
      "grouping_color_histogram_bins": 0.6577,
      "grouping_line_hough": 0.3787
    },
    "modulation_weights": {
      "contrast": [
        0.7858,
        0.9993,
        0.6977
      ],
      "symmetry": [
        0.0282,
        0.2477,
        0.588
      ],
      "isolation": [
        0.1455,
        0.4244,
        0.6713
      ],
      "grouping": [
        0.6256,
        0.4731,
        0.4453
      ]
    }
  },
  {
    "fitness": -0.9414,
    "avg_sim": 0.3560999929904938,
    "avg_cc": 0.1177,
    "avg_kl": 1.4151999950408936,
    "base_weights": {
      "contrast_edge_luminance_laplacian": 0.5471,
      "contrast_edge_luminance_sobel": 0.708,
      "contrast_edge_color_sobel": 0.2402,
      "contrast_edge_color_gradient": 0.9376,
      "contrast_region_color_slic": 0.6317,
      "contrast_texture_gabor": 0.2554,
      "contrast_texture_lbp": 0.8133,
      "contrast_texture_entropy": 0.5358,
      "symmetry_watershed": 0.2276,
      "symmetry_felzenszwalb": 0.2199,
      "symmetry_seeded_region": 0.7291,
      "symmetry_superpixel_preproc": 0.6837,
      "symmetry_superpixel": 0.4288,
      "symmetry_watershed_h": 0.32,
      "symmetry_felzenszwalb_h": 0.1747,
      "symmetry_seeded_region_h": 0.0576,
      "symmetry_superpixel_preproc_h": 0.5307,
      "symmetry_superpixel_h": 0.1385,
      "isolation_color_global_abs": 0.7204,
      "isolation_color_local_abs": 0.9319,
      "isolation_color_local_multi": 0.5636,
      "isolation_intensity_global_abs": 0.483,
      "isolation_intensity_local_abs": 0.5574,
      "isolation_intensity_local_multi": 0.0954,
      "isolation_tex_entropy_global_abs": 0.0135,
      "isolation_tex_entropy_local_abs": 0.1814,
      "isolation_tex_entropy_local_multi": 0.9981,
      "isolation_tex_lbp_global_abs": 0.4006,
      "isolation_tex_lbp_local_abs": 0.5152,
      "isolation_tex_lbp_local_multi": 0.8307,
      "isolation_tex_gab_global_abs": 0.4508,
      "isolation_tex_gab_local_abs": 0.8601,
      "isolation_tex_gab_local_multi": 0.6937,
      "grouping_color_histogram_bins": 0.3659,
      "grouping_line_hough": 0.3227
    },
    "modulation_weights": {
      "contrast": [
        0.3945,
        0.6899,
        0.4507
      ],
      "symmetry": [
        0.2201,
        0.3204,
        0.9824
      ],
      "isolation": [
        0.7993,
        0.5843,
        0.7224
      ],
      "grouping": [
        0.2972,
        0.9043,
        0.0774
      ]
    }
  },
  {
    "fitness": -0.9414,
    "avg_sim": 0.3560999929904938,
    "avg_cc": 0.1177,
    "avg_kl": 1.4151999950408936,
    "base_weights": {
      "contrast_edge_luminance_laplacian": 0.5471,
      "contrast_edge_luminance_sobel": 0.708,
      "contrast_edge_color_sobel": 0.2402,
      "contrast_edge_color_gradient": 0.9376,
      "contrast_region_color_slic": 0.6317,
      "contrast_texture_gabor": 0.2554,
      "contrast_texture_lbp": 0.8133,
      "contrast_texture_entropy": 0.5358,
      "symmetry_watershed": 0.2276,
      "symmetry_felzenszwalb": 0.2199,
      "symmetry_seeded_region": 0.7291,
      "symmetry_superpixel_preproc": 0.6837,
      "symmetry_superpixel": 0.4288,
      "symmetry_watershed_h": 0.32,
      "symmetry_felzenszwalb_h": 0.1747,
      "symmetry_seeded_region_h": 0.0576,
      "symmetry_superpixel_preproc_h": 0.5307,
      "symmetry_superpixel_h": 0.1385,
      "isolation_color_global_abs": 0.7204,
      "isolation_color_local_abs": 0.9319,
      "isolation_color_local_multi": 0.5636,
      "isolation_intensity_global_abs": 0.483,
      "isolation_intensity_local_abs": 0.5574,
      "isolation_intensity_local_multi": 0.0954,
      "isolation_tex_entropy_global_abs": 0.0135,
      "isolation_tex_entropy_local_abs": 0.1814,
      "isolation_tex_entropy_local_multi": 0.9981,
      "isolation_tex_lbp_global_abs": 0.4006,
      "isolation_tex_lbp_local_abs": 0.5152,
      "isolation_tex_lbp_local_multi": 0.8307,
      "isolation_tex_gab_global_abs": 0.4508,
      "isolation_tex_gab_local_abs": 0.8601,
      "isolation_tex_gab_local_multi": 0.6937,
      "grouping_color_histogram_bins": 0.3659,
      "grouping_line_hough": 0.3227
    },
    "modulation_weights": {
      "contrast": [
        0.3945,
        0.6899,
        0.4507
      ],
      "symmetry": [
        0.2201,
        0.3204,
        0.9824
      ],
      "isolation": [
        0.7993,
        0.5843,
        0.7224
      ],
      "grouping": [
        0.2972,
        0.9043,
        0.0774
      ]
    }
  },
  {
    "fitness": -0.9432,
    "avg_sim": 0.3562000095844269,
    "avg_cc": 0.12,
    "avg_kl": 1.4193999767303467,
    "base_weights": {
      "contrast_edge_luminance_laplacian": 0.492,
      "contrast_edge_luminance_sobel": 0.9714,
      "contrast_edge_color_sobel": 0.2431,
      "contrast_edge_color_gradient": 0.2025,
      "contrast_region_color_slic": 0.0735,
      "contrast_texture_gabor": 0.6823,
      "contrast_texture_lbp": 0.3517,
      "contrast_texture_entropy": 0.0213,
      "symmetry_watershed": 0.9085,
      "symmetry_felzenszwalb": 0.4806,
      "symmetry_seeded_region": 0.608,
      "symmetry_superpixel_preproc": 0.6422,
      "symmetry_superpixel": 0.3475,
      "symmetry_watershed_h": 0.3816,
      "symmetry_felzenszwalb_h": 0.4272,
      "symmetry_seeded_region_h": 0.4999,
      "symmetry_superpixel_preproc_h": 0.5497,
      "symmetry_superpixel_h": 0.3819,
      "isolation_color_global_abs": 0.4684,
      "isolation_color_local_abs": 0.4859,
      "isolation_color_local_multi": 0.0513,
      "isolation_intensity_global_abs": 0.1815,
      "isolation_intensity_local_abs": 0.5247,
      "isolation_intensity_local_multi": 0.761,
      "isolation_tex_entropy_global_abs": 0.2735,
      "isolation_tex_entropy_local_abs": 0.1482,
      "isolation_tex_entropy_local_multi": 0.0864,
      "isolation_tex_lbp_global_abs": 0.4327,
      "isolation_tex_lbp_local_abs": 0.3136,
      "isolation_tex_lbp_local_multi": 0.9268,
      "isolation_tex_gab_global_abs": 0.0043,
      "isolation_tex_gab_local_abs": 0.4687,
      "isolation_tex_gab_local_multi": 0.9313,
      "grouping_color_histogram_bins": 0.4157,
      "grouping_line_hough": 0.299
    },
    "modulation_weights": {
      "contrast": [
        0.8142,
        0.8986,
        0.5307
      ],
      "symmetry": [
        0.0809,
        0.0968,
        0.8937
      ],
      "isolation": [
        0.6678,
        0.9978,
        0.1969
      ],
      "grouping": [
        0.3287,
        0.647,
        0.6381
      ]
    }
  },
  {
    "fitness": -0.9432,
    "avg_sim": 0.3562000095844269,
    "avg_cc": 0.12,
    "avg_kl": 1.4193999767303467,
    "base_weights": {
      "contrast_edge_luminance_laplacian": 0.492,
      "contrast_edge_luminance_sobel": 0.9714,
      "contrast_edge_color_sobel": 0.2431,
      "contrast_edge_color_gradient": 0.2025,
      "contrast_region_color_slic": 0.0735,
      "contrast_texture_gabor": 0.6823,
      "contrast_texture_lbp": 0.3517,
      "contrast_texture_entropy": 0.0213,
      "symmetry_watershed": 0.9085,
      "symmetry_felzenszwalb": 0.4806,
      "symmetry_seeded_region": 0.608,
      "symmetry_superpixel_preproc": 0.6422,
      "symmetry_superpixel": 0.3475,
      "symmetry_watershed_h": 0.3816,
      "symmetry_felzenszwalb_h": 0.4272,
      "symmetry_seeded_region_h": 0.4999,
      "symmetry_superpixel_preproc_h": 0.5497,
      "symmetry_superpixel_h": 0.3819,
      "isolation_color_global_abs": 0.4684,
      "isolation_color_local_abs": 0.4859,
      "isolation_color_local_multi": 0.0513,
      "isolation_intensity_global_abs": 0.1815,
      "isolation_intensity_local_abs": 0.5247,
      "isolation_intensity_local_multi": 0.761,
      "isolation_tex_entropy_global_abs": 0.2735,
      "isolation_tex_entropy_local_abs": 0.1482,
      "isolation_tex_entropy_local_multi": 0.0864,
      "isolation_tex_lbp_global_abs": 0.4327,
      "isolation_tex_lbp_local_abs": 0.3136,
      "isolation_tex_lbp_local_multi": 0.9268,
      "isolation_tex_gab_global_abs": 0.0043,
      "isolation_tex_gab_local_abs": 0.4687,
      "isolation_tex_gab_local_multi": 0.9313,
      "grouping_color_histogram_bins": 0.4157,
      "grouping_line_hough": 0.299
    },
    "modulation_weights": {
      "contrast": [
        0.8142,
        0.8986,
        0.5307
      ],
      "symmetry": [
        0.0809,
        0.0968,
        0.8937
      ],
      "isolation": [
        0.6678,
        0.9978,
        0.1969
      ],
      "grouping": [
        0.3287,
        0.647,
        0.6381
      ]
    }
  },
  {
    "fitness": -0.9505,
    "avg_sim": 0.35530000925064087,
    "avg_cc": 0.1133,
    "avg_kl": 1.419100046157837,
    "base_weights": {
      "contrast_edge_luminance_laplacian": 0.2007,
      "contrast_edge_luminance_sobel": 0.4144,
      "contrast_edge_color_sobel": 0.8054,
      "contrast_edge_color_gradient": 0.4997,
      "contrast_region_color_slic": 0.9798,
      "contrast_texture_gabor": 0.8888,
      "contrast_texture_lbp": 0.0668,
      "contrast_texture_entropy": 0.1114,
      "symmetry_watershed": 0.8529,
      "symmetry_felzenszwalb": 0.2454,
      "symmetry_seeded_region": 0.1431,
      "symmetry_superpixel_preproc": 0.0547,
      "symmetry_superpixel": 0.3534,
      "symmetry_watershed_h": 0.6041,
      "symmetry_felzenszwalb_h": 0.3129,
      "symmetry_seeded_region_h": 0.6546,
      "symmetry_superpixel_preproc_h": 0.9715,
      "symmetry_superpixel_h": 0.1121,
      "isolation_color_global_abs": 0.3495,
      "isolation_color_local_abs": 0.9846,
      "isolation_color_local_multi": 0.7361,
      "isolation_intensity_global_abs": 0.2277,
      "isolation_intensity_local_abs": 0.7885,
      "isolation_intensity_local_multi": 0.6577,
      "isolation_tex_entropy_global_abs": 0.9095,
      "isolation_tex_entropy_local_abs": 0.4416,
      "isolation_tex_entropy_local_multi": 0.6379,
      "isolation_tex_lbp_global_abs": 0.846,
      "isolation_tex_lbp_local_abs": 0.3863,
      "isolation_tex_lbp_local_multi": 0.2923,
      "isolation_tex_gab_global_abs": 0.1246,
      "isolation_tex_gab_local_abs": 0.6067,
      "isolation_tex_gab_local_multi": 0.3965,
      "grouping_color_histogram_bins": 0.6321,
      "grouping_line_hough": 0.9438
    },
    "modulation_weights": {
      "contrast": [
        0.6649,
        0.883,
        0.4401
      ],
      "symmetry": [
        0.5355,
        0.0776,
        0.4734
      ],
      "isolation": [
        0.5033,
        0.7711,
        0.3167
      ],
      "grouping": [
        0.4536,
        0.4924,
        0.5749
      ]
    }
  },
  {
    "fitness": -0.9505,
    "avg_sim": 0.35530000925064087,
    "avg_cc": 0.1133,
    "avg_kl": 1.419100046157837,
    "base_weights": {
      "contrast_edge_luminance_laplacian": 0.2007,
      "contrast_edge_luminance_sobel": 0.4144,
      "contrast_edge_color_sobel": 0.8054,
      "contrast_edge_color_gradient": 0.4997,
      "contrast_region_color_slic": 0.9798,
      "contrast_texture_gabor": 0.8888,
      "contrast_texture_lbp": 0.0668,
      "contrast_texture_entropy": 0.1114,
      "symmetry_watershed": 0.8529,
      "symmetry_felzenszwalb": 0.2454,
      "symmetry_seeded_region": 0.1431,
      "symmetry_superpixel_preproc": 0.0547,
      "symmetry_superpixel": 0.3534,
      "symmetry_watershed_h": 0.6041,
      "symmetry_felzenszwalb_h": 0.3129,
      "symmetry_seeded_region_h": 0.6546,
      "symmetry_superpixel_preproc_h": 0.9715,
      "symmetry_superpixel_h": 0.1121,
      "isolation_color_global_abs": 0.3495,
      "isolation_color_local_abs": 0.9846,
      "isolation_color_local_multi": 0.7361,
      "isolation_intensity_global_abs": 0.2277,
      "isolation_intensity_local_abs": 0.7885,
      "isolation_intensity_local_multi": 0.6577,
      "isolation_tex_entropy_global_abs": 0.9095,
      "isolation_tex_entropy_local_abs": 0.4416,
      "isolation_tex_entropy_local_multi": 0.6379,
      "isolation_tex_lbp_global_abs": 0.846,
      "isolation_tex_lbp_local_abs": 0.3863,
      "isolation_tex_lbp_local_multi": 0.2923,
      "isolation_tex_gab_global_abs": 0.1246,
      "isolation_tex_gab_local_abs": 0.6067,
      "isolation_tex_gab_local_multi": 0.3965,
      "grouping_color_histogram_bins": 0.6321,
      "grouping_line_hough": 0.9438
    },
    "modulation_weights": {
      "contrast": [
        0.6649,
        0.883,
        0.4401
      ],
      "symmetry": [
        0.5355,
        0.0776,
        0.4734
      ],
      "isolation": [
        0.5033,
        0.7711,
        0.3167
      ],
      "grouping": [
        0.4536,
        0.4924,
        0.5749
      ]
    }
  },
  {
    "fitness": -0.9532,
    "avg_sim": 0.3546000123023987,
    "avg_cc": 0.1118,
    "avg_kl": 1.419600009918213,
    "base_weights": {
      "contrast_edge_luminance_laplacian": 0.3208,
      "contrast_edge_luminance_sobel": 0.8387,
      "contrast_edge_color_sobel": 0.8682,
      "contrast_edge_color_gradient": 0.8612,
      "contrast_region_color_slic": 0.6306,
      "contrast_texture_gabor": 0.6743,
      "contrast_texture_lbp": 0.142,
      "contrast_texture_entropy": 0.3974,
      "symmetry_watershed": 0.8259,
      "symmetry_felzenszwalb": 0.6591,
      "symmetry_seeded_region": 0.7977,
      "symmetry_superpixel_preproc": 0.977,
      "symmetry_superpixel": 0.2928,
      "symmetry_watershed_h": 0.3456,
      "symmetry_felzenszwalb_h": 0.501,
      "symmetry_seeded_region_h": 0.4875,
      "symmetry_superpixel_preproc_h": 0.6487,
      "symmetry_superpixel_h": 0.4322,
      "isolation_color_global_abs": 0.4011,
      "isolation_color_local_abs": 0.3959,
      "isolation_color_local_multi": 0.5361,
      "isolation_intensity_global_abs": 0.1318,
      "isolation_intensity_local_abs": 0.7982,
      "isolation_intensity_local_multi": 0.9496,
      "isolation_tex_entropy_global_abs": 0.7473,
      "isolation_tex_entropy_local_abs": 0.5097,
      "isolation_tex_entropy_local_multi": 0.6766,
      "isolation_tex_lbp_global_abs": 0.8155,
      "isolation_tex_lbp_local_abs": 0.8493,
      "isolation_tex_lbp_local_multi": 0.7868,
      "isolation_tex_gab_global_abs": 0.31,
      "isolation_tex_gab_local_abs": 0.7205,
      "isolation_tex_gab_local_multi": 0.8588,
      "grouping_color_histogram_bins": 0.8499,
      "grouping_line_hough": 0.8099
    },
    "modulation_weights": {
      "contrast": [
        0.7038,
        0.5203,
        0.297
      ],
      "symmetry": [
        0.2634,
        0.1858,
        0.8154
      ],
      "isolation": [
        0.8641,
        0.5188,
        0.2421
      ],
      "grouping": [
        0.6546,
        0.4807,
        0.2688
      ]
    }
  },
  {
    "fitness": -0.9532,
    "avg_sim": 0.3546000123023987,
    "avg_cc": 0.1118,
    "avg_kl": 1.419600009918213,
    "base_weights": {
      "contrast_edge_luminance_laplacian": 0.3208,
      "contrast_edge_luminance_sobel": 0.8387,
      "contrast_edge_color_sobel": 0.8682,
      "contrast_edge_color_gradient": 0.8612,
      "contrast_region_color_slic": 0.6306,
      "contrast_texture_gabor": 0.6743,
      "contrast_texture_lbp": 0.142,
      "contrast_texture_entropy": 0.3974,
      "symmetry_watershed": 0.8259,
      "symmetry_felzenszwalb": 0.6591,
      "symmetry_seeded_region": 0.7977,
      "symmetry_superpixel_preproc": 0.977,
      "symmetry_superpixel": 0.2928,
      "symmetry_watershed_h": 0.3456,
      "symmetry_felzenszwalb_h": 0.501,
      "symmetry_seeded_region_h": 0.4875,
      "symmetry_superpixel_preproc_h": 0.6487,
      "symmetry_superpixel_h": 0.4322,
      "isolation_color_global_abs": 0.4011,
      "isolation_color_local_abs": 0.3959,
      "isolation_color_local_multi": 0.5361,
      "isolation_intensity_global_abs": 0.1318,
      "isolation_intensity_local_abs": 0.7982,
      "isolation_intensity_local_multi": 0.9496,
      "isolation_tex_entropy_global_abs": 0.7473,
      "isolation_tex_entropy_local_abs": 0.5097,
      "isolation_tex_entropy_local_multi": 0.6766,
      "isolation_tex_lbp_global_abs": 0.8155,
      "isolation_tex_lbp_local_abs": 0.8493,
      "isolation_tex_lbp_local_multi": 0.7868,
      "isolation_tex_gab_global_abs": 0.31,
      "isolation_tex_gab_local_abs": 0.7205,
      "isolation_tex_gab_local_multi": 0.8588,
      "grouping_color_histogram_bins": 0.8499,
      "grouping_line_hough": 0.8099
    },
    "modulation_weights": {
      "contrast": [
        0.7038,
        0.5203,
        0.297
      ],
      "symmetry": [
        0.2634,
        0.1858,
        0.8154
      ],
      "isolation": [
        0.8641,
        0.5188,
        0.2421
      ],
      "grouping": [
        0.6546,
        0.4807,
        0.2688
      ]
    }
  },
  {
    "fitness": -0.9586,
    "avg_sim": 0.3546000123023987,
    "avg_cc": 0.1064,
    "avg_kl": 1.419600009918213,
    "base_weights": {
      "contrast_edge_luminance_laplacian": 0.7208,
      "contrast_edge_luminance_sobel": 0.5796,
      "contrast_edge_color_sobel": 0.2568,
      "contrast_edge_color_gradient": 0.1199,
      "contrast_region_color_slic": 0.3129,
      "contrast_texture_gabor": 0.1162,
      "contrast_texture_lbp": 0.2167,
      "contrast_texture_entropy": 0.855,
      "symmetry_watershed": 0.5651,
      "symmetry_felzenszwalb": 0.129,
      "symmetry_seeded_region": 0.8853,
      "symmetry_superpixel_preproc": 0.8164,
      "symmetry_superpixel": 0.602,
      "symmetry_watershed_h": 0.1133,
      "symmetry_felzenszwalb_h": 0.3683,
      "symmetry_seeded_region_h": 0.7744,
      "symmetry_superpixel_preproc_h": 0.1063,
      "symmetry_superpixel_h": 0.0727,
      "isolation_color_global_abs": 0.8471,
      "isolation_color_local_abs": 0.9892,
      "isolation_color_local_multi": 0.0389,
      "isolation_intensity_global_abs": 0.7261,
      "isolation_intensity_local_abs": 0.2722,
      "isolation_intensity_local_multi": 0.0343,
      "isolation_tex_entropy_global_abs": 0.6955,
      "isolation_tex_entropy_local_abs": 0.3264,
      "isolation_tex_entropy_local_multi": 0.2338,
      "isolation_tex_lbp_global_abs": 0.4114,
      "isolation_tex_lbp_local_abs": 0.2395,
      "isolation_tex_lbp_local_multi": 0.3994,
      "isolation_tex_gab_global_abs": 0.6369,
      "isolation_tex_gab_local_abs": 0.751,
      "isolation_tex_gab_local_multi": 0.602,
      "grouping_color_histogram_bins": 0.9396,
      "grouping_line_hough": 0.882
    },
    "modulation_weights": {
      "contrast": [
        0.0997,
        0.2526,
        0.9696
      ],
      "symmetry": [
        0.1757,
        0.7438,
        0.1006
      ],
      "isolation": [
        0.8829,
        0.1929,
        0.9753
      ],
      "grouping": [
        0.1304,
        0.7687,
        0.0599
      ]
    }
  },
  {
    "fitness": -0.9586,
    "avg_sim": 0.3546000123023987,
    "avg_cc": 0.1064,
    "avg_kl": 1.419600009918213,
    "base_weights": {
      "contrast_edge_luminance_laplacian": 0.7208,
      "contrast_edge_luminance_sobel": 0.5796,
      "contrast_edge_color_sobel": 0.2568,
      "contrast_edge_color_gradient": 0.1199,
      "contrast_region_color_slic": 0.3129,
      "contrast_texture_gabor": 0.1162,
      "contrast_texture_lbp": 0.2167,
      "contrast_texture_entropy": 0.855,
      "symmetry_watershed": 0.5651,
      "symmetry_felzenszwalb": 0.129,
      "symmetry_seeded_region": 0.8853,
      "symmetry_superpixel_preproc": 0.8164,
      "symmetry_superpixel": 0.602,
      "symmetry_watershed_h": 0.1133,
      "symmetry_felzenszwalb_h": 0.3683,
      "symmetry_seeded_region_h": 0.7744,
      "symmetry_superpixel_preproc_h": 0.1063,
      "symmetry_superpixel_h": 0.0727,
      "isolation_color_global_abs": 0.8471,
      "isolation_color_local_abs": 0.9892,
      "isolation_color_local_multi": 0.0389,
      "isolation_intensity_global_abs": 0.7261,
      "isolation_intensity_local_abs": 0.2722,
      "isolation_intensity_local_multi": 0.0343,
      "isolation_tex_entropy_global_abs": 0.6955,
      "isolation_tex_entropy_local_abs": 0.3264,
      "isolation_tex_entropy_local_multi": 0.2338,
      "isolation_tex_lbp_global_abs": 0.4114,
      "isolation_tex_lbp_local_abs": 0.2395,
      "isolation_tex_lbp_local_multi": 0.3994,
      "isolation_tex_gab_global_abs": 0.6369,
      "isolation_tex_gab_local_abs": 0.751,
      "isolation_tex_gab_local_multi": 0.602,
      "grouping_color_histogram_bins": 0.9396,
      "grouping_line_hough": 0.882
    },
    "modulation_weights": {
      "contrast": [
        0.0997,
        0.2526,
        0.9696
      ],
      "symmetry": [
        0.1757,
        0.7438,
        0.1006
      ],
      "isolation": [
        0.8829,
        0.1929,
        0.9753
      ],
      "grouping": [
        0.1304,
        0.7687,
        0.0599
      ]
    }
  },
  {
    "fitness": -0.9624,
    "avg_sim": 0.3544999957084656,
    "avg_cc": 0.1089,
    "avg_kl": 1.4257999658584595,
    "base_weights": {
      "contrast_edge_luminance_laplacian": 0.3784,
      "contrast_edge_luminance_sobel": 0.5115,
      "contrast_edge_color_sobel": 0.6342,
      "contrast_edge_color_gradient": 0.3403,
      "contrast_region_color_slic": 0.2579,
      "contrast_texture_gabor": 0.7594,
      "contrast_texture_lbp": 0.2557,
      "contrast_texture_entropy": 0.7727,
      "symmetry_watershed": 0.2331,
      "symmetry_felzenszwalb": 0.1963,
      "symmetry_seeded_region": 0.5876,
      "symmetry_superpixel_preproc": 0.3437,
      "symmetry_superpixel": 0.6242,
      "symmetry_watershed_h": 0.8186,
      "symmetry_felzenszwalb_h": 0.1197,
      "symmetry_seeded_region_h": 0.0168,
      "symmetry_superpixel_preproc_h": 0.3776,
      "symmetry_superpixel_h": 0.3465,
      "isolation_color_global_abs": 0.6585,
      "isolation_color_local_abs": 0.1836,
      "isolation_color_local_multi": 0.629,
      "isolation_intensity_global_abs": 0.6861,
      "isolation_intensity_local_abs": 0.0191,
      "isolation_intensity_local_multi": 0.2061,
      "isolation_tex_entropy_global_abs": 0.5606,
      "isolation_tex_entropy_local_abs": 0.1152,
      "isolation_tex_entropy_local_multi": 0.0528,
      "isolation_tex_lbp_global_abs": 0.6519,
      "isolation_tex_lbp_local_abs": 0.9976,
      "isolation_tex_lbp_local_multi": 0.9986,
      "isolation_tex_gab_global_abs": 0.2469,
      "isolation_tex_gab_local_abs": 0.8375,
      "isolation_tex_gab_local_multi": 0.4954,
      "grouping_color_histogram_bins": 0.4919,
      "grouping_line_hough": 0.1297
    },
    "modulation_weights": {
      "contrast": [
        0.384,
        0.9395,
        0.219
      ],
      "symmetry": [
        0.9199,
        0.0407,
        0.3682
      ],
      "isolation": [
        0.7,
        0.179,
        0.3958
      ],
      "grouping": [
        0.9664,
        0.3023,
        0.0454
      ]
    }
  },
  {
    "fitness": -0.9624,
    "avg_sim": 0.3544999957084656,
    "avg_cc": 0.1089,
    "avg_kl": 1.4257999658584595,
    "base_weights": {
      "contrast_edge_luminance_laplacian": 0.3784,
      "contrast_edge_luminance_sobel": 0.5115,
      "contrast_edge_color_sobel": 0.6342,
      "contrast_edge_color_gradient": 0.3403,
      "contrast_region_color_slic": 0.2579,
      "contrast_texture_gabor": 0.7594,
      "contrast_texture_lbp": 0.2557,
      "contrast_texture_entropy": 0.7727,
      "symmetry_watershed": 0.2331,
      "symmetry_felzenszwalb": 0.1963,
      "symmetry_seeded_region": 0.5876,
      "symmetry_superpixel_preproc": 0.3437,
      "symmetry_superpixel": 0.6242,
      "symmetry_watershed_h": 0.8186,
      "symmetry_felzenszwalb_h": 0.1197,
      "symmetry_seeded_region_h": 0.0168,
      "symmetry_superpixel_preproc_h": 0.3776,
      "symmetry_superpixel_h": 0.3465,
      "isolation_color_global_abs": 0.6585,
      "isolation_color_local_abs": 0.1836,
      "isolation_color_local_multi": 0.629,
      "isolation_intensity_global_abs": 0.6861,
      "isolation_intensity_local_abs": 0.0191,
      "isolation_intensity_local_multi": 0.2061,
      "isolation_tex_entropy_global_abs": 0.5606,
      "isolation_tex_entropy_local_abs": 0.1152,
      "isolation_tex_entropy_local_multi": 0.0528,
      "isolation_tex_lbp_global_abs": 0.6519,
      "isolation_tex_lbp_local_abs": 0.9976,
      "isolation_tex_lbp_local_multi": 0.9986,
      "isolation_tex_gab_global_abs": 0.2469,
      "isolation_tex_gab_local_abs": 0.8375,
      "isolation_tex_gab_local_multi": 0.4954,
      "grouping_color_histogram_bins": 0.4919,
      "grouping_line_hough": 0.1297
    },
    "modulation_weights": {
      "contrast": [
        0.384,
        0.9395,
        0.219
      ],
      "symmetry": [
        0.9199,
        0.0407,
        0.3682
      ],
      "isolation": [
        0.7,
        0.179,
        0.3958
      ],
      "grouping": [
        0.9664,
        0.3023,
        0.0454
      ]
    }
  },
  {
    "fitness": -0.968,
    "avg_sim": 0.35350000858306885,
    "avg_cc": 0.1054,
    "avg_kl": 1.4270000457763672,
    "base_weights": {
      "contrast_edge_luminance_laplacian": 0.1773,
      "contrast_edge_luminance_sobel": 0.2352,
      "contrast_edge_color_sobel": 0.6919,
      "contrast_edge_color_gradient": 0.4238,
      "contrast_region_color_slic": 0.1288,
      "contrast_texture_gabor": 0.1129,
      "contrast_texture_lbp": 0.0571,
      "contrast_texture_entropy": 0.7461,
      "symmetry_watershed": 0.6486,
      "symmetry_felzenszwalb": 0.0892,
      "symmetry_seeded_region": 0.9401,
      "symmetry_superpixel_preproc": 0.4178,
      "symmetry_superpixel": 0.5365,
      "symmetry_watershed_h": 0.9531,
      "symmetry_felzenszwalb_h": 0.1585,
      "symmetry_seeded_region_h": 0.2526,
      "symmetry_superpixel_preproc_h": 0.1728,
      "symmetry_superpixel_h": 0.6753,
      "isolation_color_global_abs": 0.9106,
      "isolation_color_local_abs": 0.9029,
      "isolation_color_local_multi": 0.3022,
      "isolation_intensity_global_abs": 0.3028,
      "isolation_intensity_local_abs": 0.5119,
      "isolation_intensity_local_multi": 0.0299,
      "isolation_tex_entropy_global_abs": 0.752,
      "isolation_tex_entropy_local_abs": 0.5976,
      "isolation_tex_entropy_local_multi": 0.4464,
      "isolation_tex_lbp_global_abs": 0.4398,
      "isolation_tex_lbp_local_abs": 0.6312,
      "isolation_tex_lbp_local_multi": 0.0246,
      "isolation_tex_gab_global_abs": 0.6285,
      "isolation_tex_gab_local_abs": 0.521,
      "isolation_tex_gab_local_multi": 0.6959,
      "grouping_color_histogram_bins": 0.2906,
      "grouping_line_hough": 0.0013
    },
    "modulation_weights": {
      "contrast": [
        0.9169,
        0.6107,
        0.3745
      ],
      "symmetry": [
        0.6425,
        0.5948,
        0.4975
      ],
      "isolation": [
        0.7043,
        0.0371,
        0.7974
      ],
      "grouping": [
        0.869,
        0.0919,
        0.5675
      ]
    }
  },
  {
    "fitness": -0.968,
    "avg_sim": 0.35350000858306885,
    "avg_cc": 0.1054,
    "avg_kl": 1.4270000457763672,
    "base_weights": {
      "contrast_edge_luminance_laplacian": 0.1773,
      "contrast_edge_luminance_sobel": 0.2352,
      "contrast_edge_color_sobel": 0.6919,
      "contrast_edge_color_gradient": 0.4238,
      "contrast_region_color_slic": 0.1288,
      "contrast_texture_gabor": 0.1129,
      "contrast_texture_lbp": 0.0571,
      "contrast_texture_entropy": 0.7461,
      "symmetry_watershed": 0.6486,
      "symmetry_felzenszwalb": 0.0892,
      "symmetry_seeded_region": 0.9401,
      "symmetry_superpixel_preproc": 0.4178,
      "symmetry_superpixel": 0.5365,
      "symmetry_watershed_h": 0.9531,
      "symmetry_felzenszwalb_h": 0.1585,
      "symmetry_seeded_region_h": 0.2526,
      "symmetry_superpixel_preproc_h": 0.1728,
      "symmetry_superpixel_h": 0.6753,
      "isolation_color_global_abs": 0.9106,
      "isolation_color_local_abs": 0.9029,
      "isolation_color_local_multi": 0.3022,
      "isolation_intensity_global_abs": 0.3028,
      "isolation_intensity_local_abs": 0.5119,
      "isolation_intensity_local_multi": 0.0299,
      "isolation_tex_entropy_global_abs": 0.752,
      "isolation_tex_entropy_local_abs": 0.5976,
      "isolation_tex_entropy_local_multi": 0.4464,
      "isolation_tex_lbp_global_abs": 0.4398,
      "isolation_tex_lbp_local_abs": 0.6312,
      "isolation_tex_lbp_local_multi": 0.0246,
      "isolation_tex_gab_global_abs": 0.6285,
      "isolation_tex_gab_local_abs": 0.521,
      "isolation_tex_gab_local_multi": 0.6959,
      "grouping_color_histogram_bins": 0.2906,
      "grouping_line_hough": 0.0013
    },
    "modulation_weights": {
      "contrast": [
        0.9169,
        0.6107,
        0.3745
      ],
      "symmetry": [
        0.6425,
        0.5948,
        0.4975
      ],
      "isolation": [
        0.7043,
        0.0371,
        0.7974
      ],
      "grouping": [
        0.869,
        0.0919,
        0.5675
      ]
    }
  },
  {
    "fitness": -0.9755,
    "avg_sim": 0.3538999855518341,
    "avg_cc": 0.1069,
    "avg_kl": 1.436400055885315,
    "base_weights": {
      "contrast_edge_luminance_laplacian": 0.9016,
      "contrast_edge_luminance_sobel": 0.6659,
      "contrast_edge_color_sobel": 0.1436,
      "contrast_edge_color_gradient": 0.491,
      "contrast_region_color_slic": 0.1016,
      "contrast_texture_gabor": 0.7402,
      "contrast_texture_lbp": 0.3862,
      "contrast_texture_entropy": 0.2554,
      "symmetry_watershed": 0.1981,
      "symmetry_felzenszwalb": 0.5063,
      "symmetry_seeded_region": 0.1663,
      "symmetry_superpixel_preproc": 0.0403,
      "symmetry_superpixel": 0.2478,
      "symmetry_watershed_h": 0.1337,
      "symmetry_felzenszwalb_h": 0.3329,
      "symmetry_seeded_region_h": 0.238,
      "symmetry_superpixel_preproc_h": 0.0299,
      "symmetry_superpixel_h": 0.6538,
      "isolation_color_global_abs": 0.084,
      "isolation_color_local_abs": 0.4914,
      "isolation_color_local_multi": 0.5966,
      "isolation_intensity_global_abs": 0.9417,
      "isolation_intensity_local_abs": 0.3104,
      "isolation_intensity_local_multi": 0.3404,
      "isolation_tex_entropy_global_abs": 0.3236,
      "isolation_tex_entropy_local_abs": 0.2494,
      "isolation_tex_entropy_local_multi": 0.5314,
      "isolation_tex_lbp_global_abs": 0.9201,
      "isolation_tex_lbp_local_abs": 0.5524,
      "isolation_tex_lbp_local_multi": 0.7212,
      "isolation_tex_gab_global_abs": 0.4692,
      "isolation_tex_gab_local_abs": 0.6781,
      "isolation_tex_gab_local_multi": 0.3942,
      "grouping_color_histogram_bins": 0.9255,
      "grouping_line_hough": 0.8597
    },
    "modulation_weights": {
      "contrast": [
        0.3223,
        0.532,
        0.7338
      ],
      "symmetry": [
        0.1804,
        0.6131,
        0.75
      ],
      "isolation": [
        0.7243,
        0.5826,
        0.761
      ],
      "grouping": [
        0.9909,
        0.0865,
        0.8635
      ]
    }
  },
  {
    "fitness": -0.9755,
    "avg_sim": 0.3538999855518341,
    "avg_cc": 0.1069,
    "avg_kl": 1.436400055885315,
    "base_weights": {
      "contrast_edge_luminance_laplacian": 0.9016,
      "contrast_edge_luminance_sobel": 0.6659,
      "contrast_edge_color_sobel": 0.1436,
      "contrast_edge_color_gradient": 0.491,
      "contrast_region_color_slic": 0.1016,
      "contrast_texture_gabor": 0.7402,
      "contrast_texture_lbp": 0.3862,
      "contrast_texture_entropy": 0.2554,
      "symmetry_watershed": 0.1981,
      "symmetry_felzenszwalb": 0.5063,
      "symmetry_seeded_region": 0.1663,
      "symmetry_superpixel_preproc": 0.0403,
      "symmetry_superpixel": 0.2478,
      "symmetry_watershed_h": 0.1337,
      "symmetry_felzenszwalb_h": 0.3329,
      "symmetry_seeded_region_h": 0.238,
      "symmetry_superpixel_preproc_h": 0.0299,
      "symmetry_superpixel_h": 0.6538,
      "isolation_color_global_abs": 0.084,
      "isolation_color_local_abs": 0.4914,
      "isolation_color_local_multi": 0.5966,
      "isolation_intensity_global_abs": 0.9417,
      "isolation_intensity_local_abs": 0.3104,
      "isolation_intensity_local_multi": 0.3404,
      "isolation_tex_entropy_global_abs": 0.3236,
      "isolation_tex_entropy_local_abs": 0.2494,
      "isolation_tex_entropy_local_multi": 0.5314,
      "isolation_tex_lbp_global_abs": 0.9201,
      "isolation_tex_lbp_local_abs": 0.5524,
      "isolation_tex_lbp_local_multi": 0.7212,
      "isolation_tex_gab_global_abs": 0.4692,
      "isolation_tex_gab_local_abs": 0.6781,
      "isolation_tex_gab_local_multi": 0.3942,
      "grouping_color_histogram_bins": 0.9255,
      "grouping_line_hough": 0.8597
    },
    "modulation_weights": {
      "contrast": [
        0.3223,
        0.532,
        0.7338
      ],
      "symmetry": [
        0.1804,
        0.6131,
        0.75
      ],
      "isolation": [
        0.7243,
        0.5826,
        0.761
      ],
      "grouping": [
        0.9909,
        0.0865,
        0.8635
      ]
    }
  },
  {
    "fitness": -0.9788,
    "avg_sim": 0.3528999984264374,
    "avg_cc": 0.1076,
    "avg_kl": 1.4392999410629272,
    "base_weights": {
      "contrast_edge_luminance_laplacian": 0.5532,
      "contrast_edge_luminance_sobel": 0.1231,
      "contrast_edge_color_sobel": 0.5149,
      "contrast_edge_color_gradient": 0.8864,
      "contrast_region_color_slic": 0.9133,
      "contrast_texture_gabor": 0.7604,
      "contrast_texture_lbp": 0.5826,
      "contrast_texture_entropy": 0.9546,
      "symmetry_watershed": 0.8674,
      "symmetry_felzenszwalb": 0.667,
      "symmetry_seeded_region": 0.103,
      "symmetry_superpixel_preproc": 0.0901,
      "symmetry_superpixel": 0.8088,
      "symmetry_watershed_h": 0.3294,
      "symmetry_felzenszwalb_h": 0.4374,
      "symmetry_seeded_region_h": 0.035,
      "symmetry_superpixel_preproc_h": 0.6471,
      "symmetry_superpixel_h": 0.6809,
      "isolation_color_global_abs": 0.3094,
      "isolation_color_local_abs": 0.4399,
      "isolation_color_local_multi": 0.7925,
      "isolation_intensity_global_abs": 0.749,
      "isolation_intensity_local_abs": 0.3152,
      "isolation_intensity_local_multi": 0.7579,
      "isolation_tex_entropy_global_abs": 0.4848,
      "isolation_tex_entropy_local_abs": 0.4113,
      "isolation_tex_entropy_local_multi": 0.2292,
      "isolation_tex_lbp_global_abs": 0.4528,
      "isolation_tex_lbp_local_abs": 0.139,
      "isolation_tex_lbp_local_multi": 0.9402,
      "isolation_tex_gab_global_abs": 0.5569,
      "isolation_tex_gab_local_abs": 0.8875,
      "isolation_tex_gab_local_multi": 0.7803,
      "grouping_color_histogram_bins": 0.1869,
      "grouping_line_hough": 0.024
    },
    "modulation_weights": {
      "contrast": [
        0.6677,
        0.9789,
        0.5938
      ],
      "symmetry": [
        0.3743,
        0.4678,
        0.841
      ],
      "isolation": [
        0.1329,
        0.3323,
        0.5341
      ],
      "grouping": [
        0.5413,
        0.4317,
        0.6115
      ]
    }
  },
  {
    "fitness": -0.9788,
    "avg_sim": 0.3528999984264374,
    "avg_cc": 0.1076,
    "avg_kl": 1.4392999410629272,
    "base_weights": {
      "contrast_edge_luminance_laplacian": 0.5532,
      "contrast_edge_luminance_sobel": 0.1231,
      "contrast_edge_color_sobel": 0.5149,
      "contrast_edge_color_gradient": 0.8864,
      "contrast_region_color_slic": 0.9133,
      "contrast_texture_gabor": 0.7604,
      "contrast_texture_lbp": 0.5826,
      "contrast_texture_entropy": 0.9546,
      "symmetry_watershed": 0.8674,
      "symmetry_felzenszwalb": 0.667,
      "symmetry_seeded_region": 0.103,
      "symmetry_superpixel_preproc": 0.0901,
      "symmetry_superpixel": 0.8088,
      "symmetry_watershed_h": 0.3294,
      "symmetry_felzenszwalb_h": 0.4374,
      "symmetry_seeded_region_h": 0.035,
      "symmetry_superpixel_preproc_h": 0.6471,
      "symmetry_superpixel_h": 0.6809,
      "isolation_color_global_abs": 0.3094,
      "isolation_color_local_abs": 0.4399,
      "isolation_color_local_multi": 0.7925,
      "isolation_intensity_global_abs": 0.749,
      "isolation_intensity_local_abs": 0.3152,
      "isolation_intensity_local_multi": 0.7579,
      "isolation_tex_entropy_global_abs": 0.4848,
      "isolation_tex_entropy_local_abs": 0.4113,
      "isolation_tex_entropy_local_multi": 0.2292,
      "isolation_tex_lbp_global_abs": 0.4528,
      "isolation_tex_lbp_local_abs": 0.139,
      "isolation_tex_lbp_local_multi": 0.9402,
      "isolation_tex_gab_global_abs": 0.5569,
      "isolation_tex_gab_local_abs": 0.8875,
      "isolation_tex_gab_local_multi": 0.7803,
      "grouping_color_histogram_bins": 0.1869,
      "grouping_line_hough": 0.024
    },
    "modulation_weights": {
      "contrast": [
        0.6677,
        0.9789,
        0.5938
      ],
      "symmetry": [
        0.3743,
        0.4678,
        0.841
      ],
      "isolation": [
        0.1329,
        0.3323,
        0.5341
      ],
      "grouping": [
        0.5413,
        0.4317,
        0.6115
      ]
    }
  },
  {
    "fitness": -0.9788,
    "avg_sim": 0.35260000824928284,
    "avg_cc": 0.0988,
    "avg_kl": 1.4301999807357788,
    "base_weights": {
      "contrast_edge_luminance_laplacian": 0.5596,
      "contrast_edge_luminance_sobel": 0.8315,
      "contrast_edge_color_sobel": 0.6911,
      "contrast_edge_color_gradient": 0.8916,
      "contrast_region_color_slic": 0.7935,
      "contrast_texture_gabor": 0.8773,
      "contrast_texture_lbp": 0.58,
      "contrast_texture_entropy": 0.1779,
      "symmetry_watershed": 0.2955,
      "symmetry_felzenszwalb": 0.359,
      "symmetry_seeded_region": 0.1973,
      "symmetry_superpixel_preproc": 0.8406,
      "symmetry_superpixel": 0.153,
      "symmetry_watershed_h": 0.2386,
      "symmetry_felzenszwalb_h": 0.5127,
      "symmetry_seeded_region_h": 0.8717,
      "symmetry_superpixel_preproc_h": 0.663,
      "symmetry_superpixel_h": 0.1603,
      "isolation_color_global_abs": 0.8149,
      "isolation_color_local_abs": 0.0847,
      "isolation_color_local_multi": 0.4759,
      "isolation_intensity_global_abs": 0.2455,
      "isolation_intensity_local_abs": 0.0107,
      "isolation_intensity_local_multi": 0.144,
      "isolation_tex_entropy_global_abs": 0.4585,
      "isolation_tex_entropy_local_abs": 0.7884,
      "isolation_tex_entropy_local_multi": 0.7691,
      "isolation_tex_lbp_global_abs": 0.2091,
      "isolation_tex_lbp_local_abs": 0.6714,
      "isolation_tex_lbp_local_multi": 0.0723,
      "isolation_tex_gab_global_abs": 0.0444,
      "isolation_tex_gab_local_abs": 0.8343,
      "isolation_tex_gab_local_multi": 0.5088,
      "grouping_color_histogram_bins": 0.8022,
      "grouping_line_hough": 0.1025
    },
    "modulation_weights": {
      "contrast": [
        0.8449,
        0.316,
        0.3052
      ],
      "symmetry": [
        0.646,
        0.0699,
        0.871
      ],
      "isolation": [
        0.3747,
        0.8805,
        0.8141
      ],
      "grouping": [
        0.7216,
        0.7604,
        0.3082
      ]
    }
  },
  {
    "fitness": -0.9788,
    "avg_sim": 0.35260000824928284,
    "avg_cc": 0.0988,
    "avg_kl": 1.4301999807357788,
    "base_weights": {
      "contrast_edge_luminance_laplacian": 0.5596,
      "contrast_edge_luminance_sobel": 0.8315,
      "contrast_edge_color_sobel": 0.6911,
      "contrast_edge_color_gradient": 0.8916,
      "contrast_region_color_slic": 0.7935,
      "contrast_texture_gabor": 0.8773,
      "contrast_texture_lbp": 0.58,
      "contrast_texture_entropy": 0.1779,
      "symmetry_watershed": 0.2955,
      "symmetry_felzenszwalb": 0.359,
      "symmetry_seeded_region": 0.1973,
      "symmetry_superpixel_preproc": 0.8406,
      "symmetry_superpixel": 0.153,
      "symmetry_watershed_h": 0.2386,
      "symmetry_felzenszwalb_h": 0.5127,
      "symmetry_seeded_region_h": 0.8717,
      "symmetry_superpixel_preproc_h": 0.663,
      "symmetry_superpixel_h": 0.1603,
      "isolation_color_global_abs": 0.8149,
      "isolation_color_local_abs": 0.0847,
      "isolation_color_local_multi": 0.4759,
      "isolation_intensity_global_abs": 0.2455,
      "isolation_intensity_local_abs": 0.0107,
      "isolation_intensity_local_multi": 0.144,
      "isolation_tex_entropy_global_abs": 0.4585,
      "isolation_tex_entropy_local_abs": 0.7884,
      "isolation_tex_entropy_local_multi": 0.7691,
      "isolation_tex_lbp_global_abs": 0.2091,
      "isolation_tex_lbp_local_abs": 0.6714,
      "isolation_tex_lbp_local_multi": 0.0723,
      "isolation_tex_gab_global_abs": 0.0444,
      "isolation_tex_gab_local_abs": 0.8343,
      "isolation_tex_gab_local_multi": 0.5088,
      "grouping_color_histogram_bins": 0.8022,
      "grouping_line_hough": 0.1025
    },
    "modulation_weights": {
      "contrast": [
        0.8449,
        0.316,
        0.3052
      ],
      "symmetry": [
        0.646,
        0.0699,
        0.871
      ],
      "isolation": [
        0.3747,
        0.8805,
        0.8141
      ],
      "grouping": [
        0.7216,
        0.7604,
        0.3082
      ]
    }
  },
  {
    "fitness": -0.9799,
    "avg_sim": 0.3528999984264374,
    "avg_cc": 0.1012,
    "avg_kl": 1.434000015258789,
    "base_weights": {
      "contrast_edge_luminance_laplacian": 0.7093,
      "contrast_edge_luminance_sobel": 0.1037,
      "contrast_edge_color_sobel": 0.891,
      "contrast_edge_color_gradient": 0.0232,
      "contrast_region_color_slic": 0.7412,
      "contrast_texture_gabor": 0.2597,
      "contrast_texture_lbp": 0.9853,
      "contrast_texture_entropy": 0.5867,
      "symmetry_watershed": 0.4216,
      "symmetry_felzenszwalb": 0.5733,
      "symmetry_seeded_region": 0.6847,
      "symmetry_superpixel_preproc": 0.2773,
      "symmetry_superpixel": 0.7835,
      "symmetry_watershed_h": 0.3786,
      "symmetry_felzenszwalb_h": 0.7755,
      "symmetry_seeded_region_h": 0.7615,
      "symmetry_superpixel_preproc_h": 0.0146,
      "symmetry_superpixel_h": 0.9294,
      "isolation_color_global_abs": 0.7731,
      "isolation_color_local_abs": 0.5688,
      "isolation_color_local_multi": 0.4428,
      "isolation_intensity_global_abs": 0.1308,
      "isolation_intensity_local_abs": 0.7084,
      "isolation_intensity_local_multi": 0.727,
      "isolation_tex_entropy_global_abs": 0.5241,
      "isolation_tex_entropy_local_abs": 0.0603,
      "isolation_tex_entropy_local_multi": 0.04,
      "isolation_tex_lbp_global_abs": 0.5957,
      "isolation_tex_lbp_local_abs": 0.8113,
      "isolation_tex_lbp_local_multi": 0.243,
      "isolation_tex_gab_global_abs": 0.7245,
      "isolation_tex_gab_local_abs": 0.6753,
      "isolation_tex_gab_local_multi": 0.9571,
      "grouping_color_histogram_bins": 0.1868,
      "grouping_line_hough": 0.9193
    },
    "modulation_weights": {
      "contrast": [
        0.0898,
        0.7292,
        0.5759
      ],
      "symmetry": [
        0.2689,
        0.6582,
        0.7948
      ],
      "isolation": [
        0.8263,
        0.632,
        0.8746
      ],
      "grouping": [
        0.5842,
        0.7759,
        0.031
      ]
    }
  },
  {
    "fitness": -0.9799,
    "avg_sim": 0.3528999984264374,
    "avg_cc": 0.1012,
    "avg_kl": 1.434000015258789,
    "base_weights": {
      "contrast_edge_luminance_laplacian": 0.7093,
      "contrast_edge_luminance_sobel": 0.1037,
      "contrast_edge_color_sobel": 0.891,
      "contrast_edge_color_gradient": 0.0232,
      "contrast_region_color_slic": 0.7412,
      "contrast_texture_gabor": 0.2597,
      "contrast_texture_lbp": 0.9853,
      "contrast_texture_entropy": 0.5867,
      "symmetry_watershed": 0.4216,
      "symmetry_felzenszwalb": 0.5733,
      "symmetry_seeded_region": 0.6847,
      "symmetry_superpixel_preproc": 0.2773,
      "symmetry_superpixel": 0.7835,
      "symmetry_watershed_h": 0.3786,
      "symmetry_felzenszwalb_h": 0.7755,
      "symmetry_seeded_region_h": 0.7615,
      "symmetry_superpixel_preproc_h": 0.0146,
      "symmetry_superpixel_h": 0.9294,
      "isolation_color_global_abs": 0.7731,
      "isolation_color_local_abs": 0.5688,
      "isolation_color_local_multi": 0.4428,
      "isolation_intensity_global_abs": 0.1308,
      "isolation_intensity_local_abs": 0.7084,
      "isolation_intensity_local_multi": 0.727,
      "isolation_tex_entropy_global_abs": 0.5241,
      "isolation_tex_entropy_local_abs": 0.0603,
      "isolation_tex_entropy_local_multi": 0.04,
      "isolation_tex_lbp_global_abs": 0.5957,
      "isolation_tex_lbp_local_abs": 0.8113,
      "isolation_tex_lbp_local_multi": 0.243,
      "isolation_tex_gab_global_abs": 0.7245,
      "isolation_tex_gab_local_abs": 0.6753,
      "isolation_tex_gab_local_multi": 0.9571,
      "grouping_color_histogram_bins": 0.1868,
      "grouping_line_hough": 0.9193
    },
    "modulation_weights": {
      "contrast": [
        0.0898,
        0.7292,
        0.5759
      ],
      "symmetry": [
        0.2689,
        0.6582,
        0.7948
      ],
      "isolation": [
        0.8263,
        0.632,
        0.8746
      ],
      "grouping": [
        0.5842,
        0.7759,
        0.031
      ]
    }
  },
  {
    "fitness": -0.9816,
    "avg_sim": 0.352400004863739,
    "avg_cc": 0.0988,
    "avg_kl": 1.432800054550171,
    "base_weights": {
      "contrast_edge_luminance_laplacian": 0.0074,
      "contrast_edge_luminance_sobel": 0.0553,
      "contrast_edge_color_sobel": 0.3612,
      "contrast_edge_color_gradient": 0.2543,
      "contrast_region_color_slic": 0.1633,
      "contrast_texture_gabor": 0.0987,
      "contrast_texture_lbp": 0.3486,
      "contrast_texture_entropy": 0.7945,
      "symmetry_watershed": 0.1712,
      "symmetry_felzenszwalb": 0.3392,
      "symmetry_seeded_region": 0.1572,
      "symmetry_superpixel_preproc": 0.4514,
      "symmetry_superpixel": 0.3566,
      "symmetry_watershed_h": 0.6051,
      "symmetry_felzenszwalb_h": 0.6712,
      "symmetry_seeded_region_h": 0.4012,
      "symmetry_superpixel_preproc_h": 0.5032,
      "symmetry_superpixel_h": 0.5031,
      "isolation_color_global_abs": 0.045,
      "isolation_color_local_abs": 0.0805,
      "isolation_color_local_multi": 0.7057,
      "isolation_intensity_global_abs": 0.2108,
      "isolation_intensity_local_abs": 0.527,
      "isolation_intensity_local_multi": 0.1181,
      "isolation_tex_entropy_global_abs": 0.5367,
      "isolation_tex_entropy_local_abs": 0.206,
      "isolation_tex_entropy_local_multi": 0.3327,
      "isolation_tex_lbp_global_abs": 0.0544,
      "isolation_tex_lbp_local_abs": 0.1985,
      "isolation_tex_lbp_local_multi": 0.6634,
      "isolation_tex_gab_global_abs": 0.615,
      "isolation_tex_gab_local_abs": 0.9844,
      "isolation_tex_gab_local_multi": 0.1307,
      "grouping_color_histogram_bins": 0.7903,
      "grouping_line_hough": 0.638
    },
    "modulation_weights": {
      "contrast": [
        0.051,
        0.4654,
        0.2186
      ],
      "symmetry": [
        0.132,
        0.3721,
        0.6564
      ],
      "isolation": [
        0.7801,
        0.1436,
        0.7136
      ],
      "grouping": [
        0.8906,
        0.4166,
        0.2089
      ]
    }
  },
  {
    "fitness": -0.9816,
    "avg_sim": 0.352400004863739,
    "avg_cc": 0.0988,
    "avg_kl": 1.432800054550171,
    "base_weights": {
      "contrast_edge_luminance_laplacian": 0.0074,
      "contrast_edge_luminance_sobel": 0.0553,
      "contrast_edge_color_sobel": 0.3612,
      "contrast_edge_color_gradient": 0.2543,
      "contrast_region_color_slic": 0.1633,
      "contrast_texture_gabor": 0.0987,
      "contrast_texture_lbp": 0.3486,
      "contrast_texture_entropy": 0.7945,
      "symmetry_watershed": 0.1712,
      "symmetry_felzenszwalb": 0.3392,
      "symmetry_seeded_region": 0.1572,
      "symmetry_superpixel_preproc": 0.4514,
      "symmetry_superpixel": 0.3566,
      "symmetry_watershed_h": 0.6051,
      "symmetry_felzenszwalb_h": 0.6712,
      "symmetry_seeded_region_h": 0.4012,
      "symmetry_superpixel_preproc_h": 0.5032,
      "symmetry_superpixel_h": 0.5031,
      "isolation_color_global_abs": 0.045,
      "isolation_color_local_abs": 0.0805,
      "isolation_color_local_multi": 0.7057,
      "isolation_intensity_global_abs": 0.2108,
      "isolation_intensity_local_abs": 0.527,
      "isolation_intensity_local_multi": 0.1181,
      "isolation_tex_entropy_global_abs": 0.5367,
      "isolation_tex_entropy_local_abs": 0.206,
      "isolation_tex_entropy_local_multi": 0.3327,
      "isolation_tex_lbp_global_abs": 0.0544,
      "isolation_tex_lbp_local_abs": 0.1985,
      "isolation_tex_lbp_local_multi": 0.6634,
      "isolation_tex_gab_global_abs": 0.615,
      "isolation_tex_gab_local_abs": 0.9844,
      "isolation_tex_gab_local_multi": 0.1307,
      "grouping_color_histogram_bins": 0.7903,
      "grouping_line_hough": 0.638
    },
    "modulation_weights": {
      "contrast": [
        0.051,
        0.4654,
        0.2186
      ],
      "symmetry": [
        0.132,
        0.3721,
        0.6564
      ],
      "isolation": [
        0.7801,
        0.1436,
        0.7136
      ],
      "grouping": [
        0.8906,
        0.4166,
        0.2089
      ]
    }
  },
  {
    "fitness": -0.9823,
    "avg_sim": 0.35249999165534973,
    "avg_cc": 0.1054,
    "avg_kl": 1.4401999711990356,
    "base_weights": {
      "contrast_edge_luminance_laplacian": 0.353,
      "contrast_edge_luminance_sobel": 0.2836,
      "contrast_edge_color_sobel": 0.0831,
      "contrast_edge_color_gradient": 0.8639,
      "contrast_region_color_slic": 0.3806,
      "contrast_texture_gabor": 0.2863,
      "contrast_texture_lbp": 0.1169,
      "contrast_texture_entropy": 0.8423,
      "symmetry_watershed": 0.6942,
      "symmetry_felzenszwalb": 0.0327,
      "symmetry_seeded_region": 0.1926,
      "symmetry_superpixel_preproc": 0.577,
      "symmetry_superpixel": 0.5255,
      "symmetry_watershed_h": 0.0929,
      "symmetry_felzenszwalb_h": 0.6277,
      "symmetry_seeded_region_h": 0.6903,
      "symmetry_superpixel_preproc_h": 0.3455,
      "symmetry_superpixel_h": 0.9236,
      "isolation_color_global_abs": 0.5993,
      "isolation_color_local_abs": 0.8688,
      "isolation_color_local_multi": 0.5027,
      "isolation_intensity_global_abs": 0.2635,
      "isolation_intensity_local_abs": 0.8736,
      "isolation_intensity_local_multi": 0.4701,
      "isolation_tex_entropy_global_abs": 0.2731,
      "isolation_tex_entropy_local_abs": 0.5818,
      "isolation_tex_entropy_local_multi": 0.4569,
      "isolation_tex_lbp_global_abs": 0.0789,
      "isolation_tex_lbp_local_abs": 0.3997,
      "isolation_tex_lbp_local_multi": 0.1056,
      "isolation_tex_gab_global_abs": 0.3155,
      "isolation_tex_gab_local_abs": 0.4463,
      "isolation_tex_gab_local_multi": 0.6872,
      "grouping_color_histogram_bins": 0.4539,
      "grouping_line_hough": 0.5363
    },
    "modulation_weights": {
      "contrast": [
        0.8807,
        0.6576,
        0.5692
      ],
      "symmetry": [
        0.1892,
        0.6689,
        0.9367
      ],
      "isolation": [
        0.4858,
        0.2302,
        0.2062
      ],
      "grouping": [
        0.8861,
        0.5162,
        0.6985
      ]
    }
  },
  {
    "fitness": -0.9823,
    "avg_sim": 0.35249999165534973,
    "avg_cc": 0.1054,
    "avg_kl": 1.4401999711990356,
    "base_weights": {
      "contrast_edge_luminance_laplacian": 0.353,
      "contrast_edge_luminance_sobel": 0.2836,
      "contrast_edge_color_sobel": 0.0831,
      "contrast_edge_color_gradient": 0.8639,
      "contrast_region_color_slic": 0.3806,
      "contrast_texture_gabor": 0.2863,
      "contrast_texture_lbp": 0.1169,
      "contrast_texture_entropy": 0.8423,
      "symmetry_watershed": 0.6942,
      "symmetry_felzenszwalb": 0.0327,
      "symmetry_seeded_region": 0.1926,
      "symmetry_superpixel_preproc": 0.577,
      "symmetry_superpixel": 0.5255,
      "symmetry_watershed_h": 0.0929,
      "symmetry_felzenszwalb_h": 0.6277,
      "symmetry_seeded_region_h": 0.6903,
      "symmetry_superpixel_preproc_h": 0.3455,
      "symmetry_superpixel_h": 0.9236,
      "isolation_color_global_abs": 0.5993,
      "isolation_color_local_abs": 0.8688,
      "isolation_color_local_multi": 0.5027,
      "isolation_intensity_global_abs": 0.2635,
      "isolation_intensity_local_abs": 0.8736,
      "isolation_intensity_local_multi": 0.4701,
      "isolation_tex_entropy_global_abs": 0.2731,
      "isolation_tex_entropy_local_abs": 0.5818,
      "isolation_tex_entropy_local_multi": 0.4569,
      "isolation_tex_lbp_global_abs": 0.0789,
      "isolation_tex_lbp_local_abs": 0.3997,
      "isolation_tex_lbp_local_multi": 0.1056,
      "isolation_tex_gab_global_abs": 0.3155,
      "isolation_tex_gab_local_abs": 0.4463,
      "isolation_tex_gab_local_multi": 0.6872,
      "grouping_color_histogram_bins": 0.4539,
      "grouping_line_hough": 0.5363
    },
    "modulation_weights": {
      "contrast": [
        0.8807,
        0.6576,
        0.5692
      ],
      "symmetry": [
        0.1892,
        0.6689,
        0.9367
      ],
      "isolation": [
        0.4858,
        0.2302,
        0.2062
      ],
      "grouping": [
        0.8861,
        0.5162,
        0.6985
      ]
    }
  },
  {
    "fitness": -0.9836,
    "avg_sim": 0.3522000014781952,
    "avg_cc": 0.0977,
    "avg_kl": 1.4335999488830566,
    "base_weights": {
      "contrast_edge_luminance_laplacian": 0.6603,
      "contrast_edge_luminance_sobel": 0.1926,
      "contrast_edge_color_sobel": 0.7367,
      "contrast_edge_color_gradient": 0.8579,
      "contrast_region_color_slic": 0.0636,
      "contrast_texture_gabor": 0.9151,
      "contrast_texture_lbp": 0.8575,
      "contrast_texture_entropy": 0.5276,
      "symmetry_watershed": 0.7763,
      "symmetry_felzenszwalb": 0.4329,
      "symmetry_seeded_region": 0.3736,
      "symmetry_superpixel_preproc": 0.8025,
      "symmetry_superpixel": 0.6241,
      "symmetry_watershed_h": 0.4948,
      "symmetry_felzenszwalb_h": 0.7287,
      "symmetry_seeded_region_h": 0.3985,
      "symmetry_superpixel_preproc_h": 0.9623,
      "symmetry_superpixel_h": 0.6801,
      "isolation_color_global_abs": 0.9717,
      "isolation_color_local_abs": 0.5889,
      "isolation_color_local_multi": 0.9109,
      "isolation_intensity_global_abs": 0.4359,
      "isolation_intensity_local_abs": 0.928,
      "isolation_intensity_local_multi": 0.0457,
      "isolation_tex_entropy_global_abs": 0.8366,
      "isolation_tex_entropy_local_abs": 0.329,
      "isolation_tex_entropy_local_multi": 0.4208,
      "isolation_tex_lbp_global_abs": 0.2075,
      "isolation_tex_lbp_local_abs": 0.9338,
      "isolation_tex_lbp_local_multi": 0.6294,
      "isolation_tex_gab_global_abs": 0.1335,
      "isolation_tex_gab_local_abs": 0.8358,
      "isolation_tex_gab_local_multi": 0.7448,
      "grouping_color_histogram_bins": 0.2836,
      "grouping_line_hough": 0.3189
    },
    "modulation_weights": {
      "contrast": [
        0.8971,
        0.5877,
        0.3476
      ],
      "symmetry": [
        0.5306,
        0.478,
        0.4843
      ],
      "isolation": [
        0.9944,
        0.1143,
        0.0282
      ],
      "grouping": [
        0.4049,
        0.556,
        0.0527
      ]
    }
  },
  {
    "fitness": -0.9836,
    "avg_sim": 0.3522000014781952,
    "avg_cc": 0.0977,
    "avg_kl": 1.4335999488830566,
    "base_weights": {
      "contrast_edge_luminance_laplacian": 0.6603,
      "contrast_edge_luminance_sobel": 0.1926,
      "contrast_edge_color_sobel": 0.7367,
      "contrast_edge_color_gradient": 0.8579,
      "contrast_region_color_slic": 0.0636,
      "contrast_texture_gabor": 0.9151,
      "contrast_texture_lbp": 0.8575,
      "contrast_texture_entropy": 0.5276,
      "symmetry_watershed": 0.7763,
      "symmetry_felzenszwalb": 0.4329,
      "symmetry_seeded_region": 0.3736,
      "symmetry_superpixel_preproc": 0.8025,
      "symmetry_superpixel": 0.6241,
      "symmetry_watershed_h": 0.4948,
      "symmetry_felzenszwalb_h": 0.7287,
      "symmetry_seeded_region_h": 0.3985,
      "symmetry_superpixel_preproc_h": 0.9623,
      "symmetry_superpixel_h": 0.6801,
      "isolation_color_global_abs": 0.9717,
      "isolation_color_local_abs": 0.5889,
      "isolation_color_local_multi": 0.9109,
      "isolation_intensity_global_abs": 0.4359,
      "isolation_intensity_local_abs": 0.928,
      "isolation_intensity_local_multi": 0.0457,
      "isolation_tex_entropy_global_abs": 0.8366,
      "isolation_tex_entropy_local_abs": 0.329,
      "isolation_tex_entropy_local_multi": 0.4208,
      "isolation_tex_lbp_global_abs": 0.2075,
      "isolation_tex_lbp_local_abs": 0.9338,
      "isolation_tex_lbp_local_multi": 0.6294,
      "isolation_tex_gab_global_abs": 0.1335,
      "isolation_tex_gab_local_abs": 0.8358,
      "isolation_tex_gab_local_multi": 0.7448,
      "grouping_color_histogram_bins": 0.2836,
      "grouping_line_hough": 0.3189
    },
    "modulation_weights": {
      "contrast": [
        0.8971,
        0.5877,
        0.3476
      ],
      "symmetry": [
        0.5306,
        0.478,
        0.4843
      ],
      "isolation": [
        0.9944,
        0.1143,
        0.0282
      ],
      "grouping": [
        0.4049,
        0.556,
        0.0527
      ]
    }
  },
  {
    "fitness": -0.9845,
    "avg_sim": 0.3531000018119812,
    "avg_cc": 0.0984,
    "avg_kl": 1.4361000061035156,
    "base_weights": {
      "contrast_edge_luminance_laplacian": 0.0078,
      "contrast_edge_luminance_sobel": 0.3483,
      "contrast_edge_color_sobel": 0.6136,
      "contrast_edge_color_gradient": 0.1883,
      "contrast_region_color_slic": 0.6555,
      "contrast_texture_gabor": 0.4958,
      "contrast_texture_lbp": 0.7977,
      "contrast_texture_entropy": 0.7779,
      "symmetry_watershed": 0.5471,
      "symmetry_felzenszwalb": 0.4026,
      "symmetry_seeded_region": 0.6136,
      "symmetry_superpixel_preproc": 0.0244,
      "symmetry_superpixel": 0.5511,
      "symmetry_watershed_h": 0.0737,
      "symmetry_felzenszwalb_h": 0.3359,
      "symmetry_seeded_region_h": 0.4224,
      "symmetry_superpixel_preproc_h": 0.3358,
      "symmetry_superpixel_h": 0.8978,
      "isolation_color_global_abs": 0.3363,
      "isolation_color_local_abs": 0.0,
      "isolation_color_local_multi": 0.3073,
      "isolation_intensity_global_abs": 1.0,
      "isolation_intensity_local_abs": 0.4402,
      "isolation_intensity_local_multi": 0.644,
      "isolation_tex_entropy_global_abs": 0.1942,
      "isolation_tex_entropy_local_abs": 0.8778,
      "isolation_tex_entropy_local_multi": 0.833,
      "isolation_tex_lbp_global_abs": 0.8741,
      "isolation_tex_lbp_local_abs": 0.6424,
      "isolation_tex_lbp_local_multi": 0.0044,
      "isolation_tex_gab_global_abs": 0.5167,
      "isolation_tex_gab_local_abs": 0.9767,
      "isolation_tex_gab_local_multi": 0.1352,
      "grouping_color_histogram_bins": 0.7108,
      "grouping_line_hough": 0.0182
    },
    "modulation_weights": {
      "contrast": [
        0.0054,
        0.9139,
        0.0313
      ],
      "symmetry": [
        0.0586,
        0.3138,
        0.7445
      ],
      "isolation": [
        0.2997,
        0.5869,
        0.7865
      ],
      "grouping": [
        0.1414,
        0.1076,
        0.5208
      ]
    }
  },
  {
    "fitness": -0.9859,
    "avg_sim": 0.3529999852180481,
    "avg_cc": 0.0984,
    "avg_kl": 1.4372999668121338,
    "base_weights": {
      "contrast_edge_luminance_laplacian": 0.0078,
      "contrast_edge_luminance_sobel": 0.3483,
      "contrast_edge_color_sobel": 0.6136,
      "contrast_edge_color_gradient": 0.1883,
      "contrast_region_color_slic": 0.6555,
      "contrast_texture_gabor": 0.4958,
      "contrast_texture_lbp": 0.7977,
      "contrast_texture_entropy": 0.7779,
      "symmetry_watershed": 0.5471,
      "symmetry_felzenszwalb": 0.4026,
      "symmetry_seeded_region": 0.6136,
      "symmetry_superpixel_preproc": 0.0244,
      "symmetry_superpixel": 0.5511,
      "symmetry_watershed_h": 0.0737,
      "symmetry_felzenszwalb_h": 0.3359,
      "symmetry_seeded_region_h": 0.4224,
      "symmetry_superpixel_preproc_h": 0.3358,
      "symmetry_superpixel_h": 0.8978,
      "isolation_color_global_abs": 0.3363,
      "isolation_color_local_abs": 0.0,
      "isolation_color_local_multi": 0.3073,
      "isolation_intensity_global_abs": 1.0,
      "isolation_intensity_local_abs": 0.4402,
      "isolation_intensity_local_multi": 0.644,
      "isolation_tex_entropy_global_abs": 0.1942,
      "isolation_tex_entropy_local_abs": 0.8778,
      "isolation_tex_entropy_local_multi": 0.833,
      "isolation_tex_lbp_global_abs": 0.8741,
      "isolation_tex_lbp_local_abs": 0.6424,
      "isolation_tex_lbp_local_multi": 0.0044,
      "isolation_tex_gab_global_abs": 0.5167,
      "isolation_tex_gab_local_abs": 0.9767,
      "isolation_tex_gab_local_multi": 0.1352,
      "grouping_color_histogram_bins": 0.7108,
      "grouping_line_hough": 0.0182
    },
    "modulation_weights": {
      "contrast": [
        0.0054,
        0.9139,
        0.0313
      ],
      "symmetry": [
        0.0586,
        0.3138,
        0.7445
      ],
      "isolation": [
        0.2997,
        0.5869,
        0.7865
      ],
      "grouping": [
        0.1414,
        0.1076,
        0.5208
      ]
    }
  },
  {
    "fitness": -0.9873,
    "avg_sim": 0.3515999913215637,
    "avg_cc": 0.0952,
    "avg_kl": 1.4341000318527222,
    "base_weights": {
      "contrast_edge_luminance_laplacian": 0.6579,
      "contrast_edge_luminance_sobel": 0.2441,
      "contrast_edge_color_sobel": 0.6495,
      "contrast_edge_color_gradient": 0.6826,
      "contrast_region_color_slic": 0.4947,
      "contrast_texture_gabor": 0.1036,
      "contrast_texture_lbp": 0.0351,
      "contrast_texture_entropy": 0.7483,
      "symmetry_watershed": 0.4549,
      "symmetry_felzenszwalb": 0.2683,
      "symmetry_seeded_region": 0.4005,
      "symmetry_superpixel_preproc": 0.3866,
      "symmetry_superpixel": 0.2295,
      "symmetry_watershed_h": 0.0594,
      "symmetry_felzenszwalb_h": 0.5098,
      "symmetry_seeded_region_h": 0.6355,
      "symmetry_superpixel_preproc_h": 0.2126,
      "symmetry_superpixel_h": 0.5262,
      "isolation_color_global_abs": 0.795,
      "isolation_color_local_abs": 0.7805,
      "isolation_color_local_multi": 0.7652,
      "isolation_intensity_global_abs": 0.0114,
      "isolation_intensity_local_abs": 0.2937,
      "isolation_intensity_local_multi": 0.7385,
      "isolation_tex_entropy_global_abs": 0.4237,
      "isolation_tex_entropy_local_abs": 0.7298,
      "isolation_tex_entropy_local_multi": 0.3525,
      "isolation_tex_lbp_global_abs": 0.2786,
      "isolation_tex_lbp_local_abs": 0.0317,
      "isolation_tex_lbp_local_multi": 0.0227,
      "isolation_tex_gab_global_abs": 0.3907,
      "isolation_tex_gab_local_abs": 0.8704,
      "isolation_tex_gab_local_multi": 0.3053,
      "grouping_color_histogram_bins": 0.1851,
      "grouping_line_hough": 0.0105
    },
    "modulation_weights": {
      "contrast": [
        0.4205,
        0.061,
        0.7221
      ],
      "symmetry": [
        0.9,
        0.1737,
        0.231
      ],
      "isolation": [
        0.9248,
        0.1036,
        0.068
      ],
      "grouping": [
        0.9801,
        0.5727,
        0.6949
      ]
    }
  },
  {
    "fitness": -0.9911,
    "avg_sim": 0.3513000011444092,
    "avg_cc": 0.0937,
    "avg_kl": 1.4361000061035156,
    "base_weights": {
      "contrast_edge_luminance_laplacian": 0.6579,
      "contrast_edge_luminance_sobel": 0.2441,
      "contrast_edge_color_sobel": 0.6495,
      "contrast_edge_color_gradient": 0.6826,
      "contrast_region_color_slic": 0.4947,
      "contrast_texture_gabor": 0.1036,
      "contrast_texture_lbp": 0.0351,
      "contrast_texture_entropy": 0.7483,
      "symmetry_watershed": 0.4549,
      "symmetry_felzenszwalb": 0.2683,
      "symmetry_seeded_region": 0.4005,
      "symmetry_superpixel_preproc": 0.3866,
      "symmetry_superpixel": 0.2295,
      "symmetry_watershed_h": 0.0594,
      "symmetry_felzenszwalb_h": 0.5098,
      "symmetry_seeded_region_h": 0.6355,
      "symmetry_superpixel_preproc_h": 0.2126,
      "symmetry_superpixel_h": 0.5262,
      "isolation_color_global_abs": 0.795,
      "isolation_color_local_abs": 0.7805,
      "isolation_color_local_multi": 0.7652,
      "isolation_intensity_global_abs": 0.0114,
      "isolation_intensity_local_abs": 0.2937,
      "isolation_intensity_local_multi": 0.7385,
      "isolation_tex_entropy_global_abs": 0.4237,
      "isolation_tex_entropy_local_abs": 0.7298,
      "isolation_tex_entropy_local_multi": 0.3525,
      "isolation_tex_lbp_global_abs": 0.2786,
      "isolation_tex_lbp_local_abs": 0.0317,
      "isolation_tex_lbp_local_multi": 0.0227,
      "isolation_tex_gab_global_abs": 0.3907,
      "isolation_tex_gab_local_abs": 0.8704,
      "isolation_tex_gab_local_multi": 0.3053,
      "grouping_color_histogram_bins": 0.1851,
      "grouping_line_hough": 0.0105
    },
    "modulation_weights": {
      "contrast": [
        0.4205,
        0.061,
        0.7221
      ],
      "symmetry": [
        0.9,
        0.1737,
        0.231
      ],
      "isolation": [
        0.9248,
        0.1036,
        0.068
      ],
      "grouping": [
        0.9801,
        0.5727,
        0.6949
      ]
    }
  },
  {
    "fitness": -0.9942,
    "avg_sim": 0.3517000079154968,
    "avg_cc": 0.0954,
    "avg_kl": 1.4412000179290771,
    "base_weights": {
      "contrast_edge_luminance_laplacian": 0.3136,
      "contrast_edge_luminance_sobel": 0.9478,
      "contrast_edge_color_sobel": 0.1076,
      "contrast_edge_color_gradient": 0.8116,
      "contrast_region_color_slic": 0.3373,
      "contrast_texture_gabor": 0.6841,
      "contrast_texture_lbp": 0.2606,
      "contrast_texture_entropy": 0.6615,
      "symmetry_watershed": 0.0536,
      "symmetry_felzenszwalb": 0.3721,
      "symmetry_seeded_region": 0.2131,
      "symmetry_superpixel_preproc": 0.2255,
      "symmetry_superpixel": 0.085,
      "symmetry_watershed_h": 0.7417,
      "symmetry_felzenszwalb_h": 0.7896,
      "symmetry_seeded_region_h": 0.4418,
      "symmetry_superpixel_preproc_h": 0.0263,
      "symmetry_superpixel_h": 0.6492,
      "isolation_color_global_abs": 0.2272,
      "isolation_color_local_abs": 0.0694,
      "isolation_color_local_multi": 0.7177,
      "isolation_intensity_global_abs": 0.4927,
      "isolation_intensity_local_abs": 0.0049,
      "isolation_intensity_local_multi": 0.6079,
      "isolation_tex_entropy_global_abs": 0.8939,
      "isolation_tex_entropy_local_abs": 0.1404,
      "isolation_tex_entropy_local_multi": 0.0915,
      "isolation_tex_lbp_global_abs": 0.6109,
      "isolation_tex_lbp_local_abs": 0.9419,
      "isolation_tex_lbp_local_multi": 0.7589,
      "isolation_tex_gab_global_abs": 0.2767,
      "isolation_tex_gab_local_abs": 0.9744,
      "isolation_tex_gab_local_multi": 0.4329,
      "grouping_color_histogram_bins": 0.5987,
      "grouping_line_hough": 0.557
    },
    "modulation_weights": {
      "contrast": [
        0.8027,
        0.1263,
        0.2072
      ],
      "symmetry": [
        0.889,
        0.2167,
        0.7097
      ],
      "isolation": [
        0.5416,
        0.3698,
        0.835
      ],
      "grouping": [
        0.2989,
        0.0044,
        0.158
      ]
    }
  },
  {
    "fitness": -0.9942,
    "avg_sim": 0.3517000079154968,
    "avg_cc": 0.0954,
    "avg_kl": 1.4412000179290771,
    "base_weights": {
      "contrast_edge_luminance_laplacian": 0.3136,
      "contrast_edge_luminance_sobel": 0.9478,
      "contrast_edge_color_sobel": 0.1076,
      "contrast_edge_color_gradient": 0.8116,
      "contrast_region_color_slic": 0.3373,
      "contrast_texture_gabor": 0.6841,
      "contrast_texture_lbp": 0.2606,
      "contrast_texture_entropy": 0.6615,
      "symmetry_watershed": 0.0536,
      "symmetry_felzenszwalb": 0.3721,
      "symmetry_seeded_region": 0.2131,
      "symmetry_superpixel_preproc": 0.2255,
      "symmetry_superpixel": 0.085,
      "symmetry_watershed_h": 0.7417,
      "symmetry_felzenszwalb_h": 0.7896,
      "symmetry_seeded_region_h": 0.4418,
      "symmetry_superpixel_preproc_h": 0.0263,
      "symmetry_superpixel_h": 0.6492,
      "isolation_color_global_abs": 0.2272,
      "isolation_color_local_abs": 0.0694,
      "isolation_color_local_multi": 0.7177,
      "isolation_intensity_global_abs": 0.4927,
      "isolation_intensity_local_abs": 0.0049,
      "isolation_intensity_local_multi": 0.6079,
      "isolation_tex_entropy_global_abs": 0.8939,
      "isolation_tex_entropy_local_abs": 0.1404,
      "isolation_tex_entropy_local_multi": 0.0915,
      "isolation_tex_lbp_global_abs": 0.6109,
      "isolation_tex_lbp_local_abs": 0.9419,
      "isolation_tex_lbp_local_multi": 0.7589,
      "isolation_tex_gab_global_abs": 0.2767,
      "isolation_tex_gab_local_abs": 0.9744,
      "isolation_tex_gab_local_multi": 0.4329,
      "grouping_color_histogram_bins": 0.5987,
      "grouping_line_hough": 0.557
    },
    "modulation_weights": {
      "contrast": [
        0.8027,
        0.1263,
        0.2072
      ],
      "symmetry": [
        0.889,
        0.2167,
        0.7097
      ],
      "isolation": [
        0.5416,
        0.3698,
        0.835
      ],
      "grouping": [
        0.2989,
        0.0044,
        0.158
      ]
    }
  }
]